bjpmodel/BjpG.cpp
bjpmodel/BjpWrapper.cpp
bjpmodel/BjpWrapper.h
bjpmodel/DistributionFactory.cpp
bjpmodel/__init__.py
bjpmodel/demo.py
bjpmodel/dummy_bjp.py
bjpmodel/model.py
bjpmodel/pybjp.cp311-win32.pyd
bjpmodel/pybjp.cpp
bjpmodel-0.2.1.dist-info/METADATA
bjpmodel-0.2.1.dist-info/WHEEL
bjpmodel-0.2.1.dist-info/top_level.txt
bjpmodel-0.2.1.dist-info/RECORD
