Metadata-Version: 2.4
Name: bjpmodel
Version: 0.2.1
Summary: BJP (Bayesian Joint Probability)
Author-email: Andrew Schepen <andrew.schepen@csiro.au>
License: MIT
Requires-Python: <3.14,>=3.11
Requires-Dist: numpy>=1.26.0
Requires-Dist: cython>=3.0.12
Requires-Dist: setuptools>=79.0.1
Requires-Dist: pytest<9.0.0,>=8.3.5
Requires-Dist: twine<7.0.0,>=6.1.0
Requires-Dist: cibuildwheel<3.0.0,>=2.23.3
Requires-Dist: normtransform<0.3.0,>=0.2.0
